topological_adam/__init__.py
topological_adam/optimizer.py
topological_adam-1.0.0.dist-info/METADATA
topological_adam-1.0.0.dist-info/WHEEL
topological_adam-1.0.0.dist-info/top_level.txt
topological_adam-1.0.0.dist-info/RECORD
