Metadata-Version: 2.4
Name: topological-adam
Version: 1.0.0
Summary: Energy-Stabilized Topological Adam Optimizer (MHD-inspired)
Author: Steven Reid
Requires-Python: >=3.8
Requires-Dist: torch>=1.10
